slacktouch/__init__.py
slacktouch/slackapi.py
slacktouch-0.0.1.dist-info/METADATA
slacktouch-0.0.1.dist-info/WHEEL
slacktouch-0.0.1.dist-info/top_level.txt
slacktouch-0.0.1.dist-info/RECORD
