Metadata-Version: 2.1
Name: slacktouch
Version: 0.0.1
Summary: for slack logging
Home-page: UNKNOWN
Author: art-c
License: UNKNOWN
Keywords: pypi deploy
Platform: UNKNOWN
Requires-Python: >=3
